[{"schoolName": "\u9ed1\u9f99\u6c5f\u5927\u5b66", "spname": "\u91d1\u878d\u5b66", "average": 530, "max": 539, "min": 522}, {"schoolName": "\u9ed1\u9f99\u6c5f\u5927\u5b66", "spname": "\u4f1a\u8ba1\u5b66", "average": 529, "max": 536, "min": 524}, {"schoolName": "\u9ed1\u9f99\u6c5f\u5927\u5b66", "spname": "\u7ffb\u8bd1\uff08\u4fc4\u8bed\uff09", "average": 551, "max": 555, "min": 547}, {"schoolName": "\u9ed1\u9f99\u6c5f\u4e2d\u533b\u836f\u5927\u5b66", "spname": "\u4e2d\u897f\u533b\u4e34\u5e8a\u533b\u5b66", "average": 545, "max": 551, "min": 540}, {"schoolName": "\u957f\u5b89\u5927\u5b66", "spname": "\u65e5\u8bed\uff08\u63d0\u524d\u6279\uff09\uff08\u5206\u6d41\u4e13\u4e1a\uff1a\u65e5\u8bed\uff09", "average": 549, "max": 554, "min": 546}, {"schoolName": "\u957f\u5b89\u5927\u5b66", "spname": "\u65b0\u95fb\u4f20\u64ad\u5b66\u7c7b\uff08\u5206\u6d41\u4e13\u4e1a\uff1a\u65b0\u95fb\u5b66\u3001\u5e7f\u544a\u5b66\u3001\u6c49\u8bed\u8a00\u6587\u5b66\uff09", "average": 556, "max": 566, "min": 551}, {"schoolName": "\u957f\u5b89\u5927\u5b66", "spname": "\u82f1\u8bed\uff08\u5206\u6d41\u4e13\u4e1a\uff1a\u82f1\u8bed\uff09", "average": 555, "max": 565, "min": 552}, {"schoolName": "\u957f\u5b89\u5927\u5b66", "spname": "\u516c\u5171\u7ba1\u7406\u7c7b\uff08\u5206\u6d41\u4e13\u4e1a\uff1a\u516c\u5171\u4e8b\u4e1a\u7ba1\u7406\u3001\u884c\u653f\u7ba1\u7406\uff09", "average": 556, "max": 565, "min": 553}, {"schoolName": "\u91cd\u5e86\u5e08\u8303\u5927\u5b66", "spname": "\u6c49\u8bed\u8a00\u6587\u5b66", "average": 528, "max": 530, "min": 527}, {"schoolName": "\u91cd\u5e86\u5de5\u5546\u5927\u5b66", "spname": "\u4eba\u529b\u8d44\u6e90\u7ba1\u7406", "average": 554, "max": 554, "min": 554}, {"schoolName": "\u91cd\u5e86\u5de5\u5546\u5927\u5b66", "spname": "\u56fd\u9645\u7ecf\u6d4e\u4e0e\u8d38\u6613", "average": 555, "max": 555, "min": 555}, {"schoolName": "\u91cd\u5e86\u5de5\u5546\u5927\u5b66", "spname": "\u8d38\u6613\u7ecf\u6d4e", "average": 558, "max": 558, "min": 558}, {"schoolName": "\u8fbd\u5b81\u5927\u5b66", "spname": "\u56fd\u9645\u653f\u6cbb", "average": 554, "max": 555, "min": 552}, {"schoolName": "\u8fbd\u5b81\u5927\u5b66", "spname": "\u8003\u53e4\u5b66", "average": 553, "max": 553, "min": 553}, {"schoolName": "\u8d35\u5dde\u5927\u5b66", "spname": "\u5de5\u5546\u7ba1\u7406\u7c7b", "average": 544, "max": 554, "min": 539}, {"schoolName": "\u8d35\u5dde\u5927\u5b66", "spname": "\u7ecf\u6d4e\u4e0e\u8d38\u6613\u7c7b", "average": 543, "max": 546, "min": 540}, {"schoolName": "\u897f\u5b89\u90ae\u7535\u5927\u5b66", "spname": "\u4f1a\u8ba1\u5b66", "average": 540, "max": 547, "min": 536}, {"schoolName": "\u897f\u5b89\u7535\u5b50\u79d1\u6280\u5927\u5b66", "spname": "\u65e5\u8bed", "average": 558, "max": 560, "min": 557}, {"schoolName": "\u897f\u5b89\u5efa\u7b51\u79d1\u6280\u5927\u5b66", "spname": "\u6c49\u8bed\u8a00\u6587\u5b66\uff08\u6587\uff09", "average": 529, "max": 548, "min": 519}, {"schoolName": "\u897f\u5b89\u5efa\u7b51\u79d1\u6280\u5927\u5b66", "spname": "\u57ce\u4e61\u89c4\u5212\uff08\u6587\uff09", "average": 550, "max": 555, "min": 546}, {"schoolName": "\u9ed1\u9f99\u6c5f\u5927\u5b66", "spname": "\u7ecf\u6d4e\u5b66", "average": 529, "max": 537, "min": 521}, {"schoolName": "\u897f\u5b89\u5efa\u7b51\u79d1\u6280\u5927\u5b66", "spname": "\u98ce\u666f\u56ed\u6797\uff08\u6587\uff09", "average": 550, "max": 555, "min": 546}, {"schoolName": "\u897f\u5b89\u5916\u56fd\u8bed\u5927\u5b66", "spname": "\u65e5\u8bed", "average": 534, "max": 565, "min": 522}, {"schoolName": "\u897f\u5b89\u5916\u56fd\u8bed\u5927\u5b66", "spname": "\u4e4c\u514b\u5170\u8bed", "average": 532, "max": 544, "min": 525}, {"schoolName": "\u897f\u5b89\u5916\u56fd\u8bed\u5927\u5b66", "spname": "\u82f1\u8bed", "average": 539, "max": 562, "min": 529}, {"schoolName": "\u897f\u5b89\u5916\u56fd\u8bed\u5927\u5b66", "spname": "\u5ba1\u8ba1\u5b66", "average": 542, "max": 562, "min": 534}, {"schoolName": "\u897f\u5b89\u5916\u56fd\u8bed\u5927\u5b66", "spname": "\u4fc4\u8bed", "average": 547, "max": 577, "min": 539}, {"schoolName": "\u897f\u5b89\u5916\u56fd\u8bed\u5927\u5b66", "spname": "\u610f\u5927\u5229\u8bed", "average": 547, "max": 550, "min": 543}, {"schoolName": "\u897f\u5b89\u5916\u56fd\u8bed\u5927\u5b66", "spname": "\u4f1a\u8ba1\u5b66", "average": 550, "max": 577, "min": 543}, {"schoolName": "\u897f\u5b89\u5916\u56fd\u8bed\u5927\u5b66", "spname": "\u8461\u8404\u7259\u8bed", "average": 556, "max": 556, "min": 555}, {"schoolName": "\u897f\u5357\u77f3\u6cb9\u5927\u5b66", "spname": "\u516c\u5171\u4e8b\u4e1a\u7ba1\u7406", "average": 530, "max": 530, "min": 529}, {"schoolName": "\u897f\u5357\u77f3\u6cb9\u5927\u5b66", "spname": "\u4fc4\u8bed", "average": 530, "max": 530, "min": 530}, {"schoolName": "\u957f\u5b89\u5927\u5b66", "spname": "\u6cd5\u5b66\u7c7b\uff08\u5206\u6d41\u4e13\u4e1a\uff1a\u6cd5\u5b66\u3001\u601d\u60f3\u653f\u6cbb\u6559\u80b2\uff09", "average": 555, "max": 561, "min": 552}, {"schoolName": "\u897f\u5357\u77f3\u6cb9\u5927\u5b66", "spname": "\u5e02\u573a\u8425\u9500", "average": 538, "max": 544, "min": 532}, {"schoolName": "\u897f\u5357\u77f3\u6cb9\u5927\u5b66", "spname": "\u7ecf\u6d4e\u5b66", "average": 538, "max": 542, "min": 534}, {"schoolName": "\u897f\u5357\u77f3\u6cb9\u5927\u5b66", "spname": "\u4f1a\u8ba1\u5b66", "average": 546, "max": 546, "min": 545}, {"schoolName": "\u897f\u5317\u653f\u6cd5\u5927\u5b66", "spname": "\u52b3\u52a8\u4e0e\u793e\u4f1a\u4fdd\u969c", "average": 529, "max": 537, "min": 520}, {"schoolName": "\u897f\u5317\u653f\u6cd5\u5927\u5b66", "spname": "\u6cd5\u5b66\uff08\u7ecf\u6d4e\u6cd5\uff09", "average": 531, "max": 572, "min": 522}, {"schoolName": "\u897f\u5317\u653f\u6cd5\u5927\u5b66", "spname": "\u91d1\u878d\u5b66", "average": 533, "max": 559, "min": 524}, {"schoolName": "\u897f\u5317\u653f\u6cd5\u5927\u5b66", "spname": "\u65b0\u95fb\u5b66", "average": 533, "max": 548, "min": 527}, {"schoolName": "\u897f\u5317\u653f\u6cd5\u5927\u5b66", "spname": "\u7ecf\u6d4e\u5b66", "average": 538, "max": 558, "min": 528}, {"schoolName": "\u897f\u5317\u653f\u6cd5\u5927\u5b66", "spname": "\u6cd5\u5b66\uff08\u6c11\u5546\u6cd5\uff09", "average": 547, "max": 587, "min": 538}, {"schoolName": "\u897f\u5357\u6c11\u65cf\u5927\u5b66", "spname": "\u4f1a\u8ba1\u5b66", "average": 531, "max": 547, "min": 521}, {"schoolName": "\u897f\u5317\u519c\u6797\u79d1\u6280\u5927\u5b66", "spname": "\u5de5\u5546\u7ba1\u7406\u7c7b", "average": 538, "max": 562, "min": 531}, {"schoolName": "\u897f\u5317\u519c\u6797\u79d1\u6280\u5927\u5b66", "spname": "\u793e\u4f1a\u5b66\u7c7b", "average": 554, "max": 566, "min": 549}, {"schoolName": "\u897f\u5317\u519c\u6797\u79d1\u6280\u5927\u5b66", "spname": "\u82f1\u8bed", "average": 552, "max": 564, "min": 549}, {"schoolName": "\u897f\u5317\u519c\u6797\u79d1\u6280\u5927\u5b66", "spname": "\u6cd5\u5b66", "average": 556, "max": 574, "min": 550}, {"schoolName": "\u897f\u5317\u519c\u6797\u79d1\u6280\u5927\u5b66", "spname": "\u516c\u5171\u4e8b\u4e1a\u7ba1\u7406", "average": 556, "max": 561, "min": 552}, {"schoolName": "\u897f\u5317\u653f\u6cd5\u5927\u5b66", "spname": "\u884c\u653f\u7ba1\u7406", "average": 538, "max": 544, "min": 528}, {"schoolName": "\u71d5\u5c71\u5927\u5b66", "spname": "\u7ffb\u8bd1", "average": 540, "max": 543, "min": 537}, {"schoolName": "\u71d5\u5c71\u5927\u5b66", "spname": "\u5e7f\u64ad\u7535\u89c6\u5b66", "average": 543, "max": 544, "min": 542}, {"schoolName": "\u71d5\u5c71\u5927\u5b66", "spname": "\u6c49\u8bed\u8a00\u6587\u5b66", "average": 545, "max": 546, "min": 544}, {"schoolName": "\u6e58\u6f6d\u5927\u5b66", "spname": "\u653f\u6cbb\u5b66\u4e0e\u884c\u653f\u5b66", "average": 545, "max": 548, "min": 542}, {"schoolName": "\u6e58\u6f6d\u5927\u5b66", "spname": "\u6587\u5316\u4ea7\u4e1a\u7ba1\u7406", "average": 546, "max": 548, "min": 542}, {"schoolName": "\u6e58\u6f6d\u5927\u5b66", "spname": "\u5e7f\u544a\u5b66", "average": 542, "max": 542, "min": 542}, {"schoolName": "\u6e58\u6f6d\u5927\u5b66", "spname": "\u7535\u5b50\u5546\u52a1", "average": 545, "max": 551, "min": 542}, {"schoolName": "\u6e58\u6f6d\u5927\u5b66", "spname": "\u6c49\u8bed\u56fd\u9645\u6559\u80b2", "average": 546, "max": 546, "min": 545}, {"schoolName": "\u6e58\u6f6d\u5927\u5b66", "spname": "\u6cd5\u5b66", "average": 551, "max": 559, "min": 545}, {"schoolName": "\u8d35\u5dde\u5927\u5b66", "spname": "\u65c5\u6e38\u7ba1\u7406", "average": 544, "max": 547, "min": 540}, {"schoolName": "\u91cd\u5e86\u5de5\u5546\u5927\u5b66", "spname": "\u5ba1\u8ba1\u5b66", "average": 558, "max": 558, "min": 558}, {"schoolName": "\u897f\u5b89\u5916\u56fd\u8bed\u5927\u5b66", "spname": "\u5546\u52a1\u82f1\u8bed", "average": 544, "max": 589, "min": 537}, {"schoolName": "\u897f\u5b89\u5916\u56fd\u8bed\u5927\u5b66", "spname": "\u6cd5\u8bed", "average": 555, "max": 563, "min": 550}, {"schoolName": "\u897f\u5317\u653f\u6cd5\u5927\u5b66", "spname": "\u5ba1\u8ba1\u5b66", "average": 541, "max": 565, "min": 531}, {"schoolName": "\u6d77\u5357\u5927\u5b66", "spname": "\u5916\u56fd\u8bed\u8a00\u6587\u5b66\u7c7b", "average": 543, "max": 550, "min": 540}, {"schoolName": "\u6d77\u5357\u5927\u5b66", "spname": "\u65e5\u8bed", "average": 543, "max": 543, "min": 543}, {"schoolName": "\u6d77\u5357\u5927\u5b66", "spname": "\u601d\u60f3\u653f\u6cbb\u6559\u80b2", "average": 552, "max": 554, "min": 550}, {"schoolName": "\u6e58\u6f6d\u5927\u5b66", "spname": "\u65e5\u8bed", "average": 544, "max": 545, "min": 543}, {"schoolName": "\u6d77\u5357\u5927\u5b66", "spname": "\u6cd5\u5b66", "average": 558, "max": 562, "min": 555}, {"schoolName": "\u6d77\u5357\u5927\u5b66", "spname": "\u4fc4\u8bed", "average": 548, "max": 548, "min": 548}, {"schoolName": "\u71d5\u5c71\u5927\u5b66", "spname": "\u6cd5\u5b66", "average": 545, "max": 546, "min": 544}, {"schoolName": "\u6cb3\u5317\u5de5\u4e1a\u5927\u5b66", "spname": "\u516c\u5171\u4e8b\u4e1a\u7ba1\u7406", "average": 553, "max": 558, "min": 548}, {"schoolName": "\u6e58\u6f6d\u5927\u5b66", "spname": "\u8d22\u52a1\u7ba1\u7406", "average": 550, "max": 555, "min": 546}, {"schoolName": "\u6b66\u6c49\u79d1\u6280\u5927\u5b66", "spname": "\u82f1\u8bed", "average": 538, "max": 539, "min": 537}, {"schoolName": "\u6b66\u6c49\u79d1\u6280\u5927\u5b66", "spname": "\u5de5\u5546\u7ba1\u7406", "average": 542, "max": 542, "min": 542}, {"schoolName": "\u6b66\u6c49\u79d1\u6280\u5927\u5b66", "spname": "\u7535\u5b50\u5546\u52a1", "average": 541, "max": 541, "min": 541}, {"schoolName": "\u6e58\u6f6d\u5927\u5b66", "spname": "\u56fd\u9645\u7ecf\u6d4e\u4e0e\u8d38\u6613", "average": 544, "max": 544, "min": 543}, {"schoolName": "\u9ed1\u9f99\u6c5f\u4e2d\u533b\u836f\u5927\u5b66", "spname": "\u9488\u7078\u63a8\u62ff\u5b66", "average": 541, "max": 547, "min": 538}, {"schoolName": "\u897f\u5357\u77f3\u6cb9\u5927\u5b66", "spname": "\u56fd\u9645\u7ecf\u6d4e\u4e0e\u8d38\u6613", "average": 538, "max": 541, "min": 536}, {"schoolName": "\u6b66\u6c49\u79d1\u6280\u5927\u5b66", "spname": "\u884c\u653f\u7ba1\u7406", "average": 540, "max": 542, "min": 539}, {"schoolName": "\u6cb3\u5317\u5de5\u4e1a\u5927\u5b66", "spname": "\u6cd5\u5b66", "average": 552, "max": 556, "min": 548}, {"schoolName": "\u9ed1\u9f99\u6c5f\u5927\u5b66", "spname": "\u897f\u73ed\u7259\u8bed", "average": 534, "max": 541, "min": 526}, {"schoolName": "\u897f\u5357\u77f3\u6cb9\u5927\u5b66", "spname": "\u5de5\u5546\u7ba1\u7406", "average": 540, "max": 548, "min": 532}, {"schoolName": "\u897f\u5357\u77f3\u6cb9\u5927\u5b66", "spname": "\u6cd5\u5b66", "average": 533, "max": 536, "min": 530}, {"schoolName": "\u897f\u5b89\u5916\u56fd\u8bed\u5927\u5b66", "spname": "\u9a6c\u6765\u8bed", "average": 535, "max": 547, "min": 526}, {"schoolName": "\u5c71\u4e1c\u8d22\u7ecf\u5927\u5b66", "spname": "\u56fd\u9645\u7ecf\u6d4e\u4e0e\u8d38\u6613", "average": 530, "max": 530, "min": 530}, {"schoolName": "\u5c71\u4e1c\u5e08\u8303\u5927\u5b66", "spname": "\u65b0\u95fb\u4f20\u64ad\u5b66\u7c7b", "average": 544, "max": 548, "min": 542}, {"schoolName": "\u5c71\u4e1c\u5e08\u8303\u5927\u5b66", "spname": "\u6cd5\u5b66\u7c7b", "average": 547, "max": 554, "min": 544}, {"schoolName": "\u5c71\u4e1c\u5e08\u8303\u5927\u5b66", "spname": "\u5e7f\u64ad\u7535\u89c6\u7f16\u5bfc", "average": 546, "max": 546, "min": 544}, {"schoolName": "\u5c71\u4e1c\u5e08\u8303\u5927\u5b66", "spname": "\u5b66\u524d\u6559\u80b2", "average": 546, "max": 546, "min": 544}, {"schoolName": "\u5c71\u4e1c\u8d22\u7ecf\u5927\u5b66", "spname": "\u5de5\u5546\u7ba1\u7406", "average": 530, "max": 530, "min": 530}, {"schoolName": "\u897f\u5b89\u5916\u56fd\u8bed\u5927\u5b66", "spname": "\u7ecf\u6d4e\u5b66", "average": 534, "max": 557, "min": 523}, {"schoolName": "\u897f\u5b89\u90ae\u7535\u5927\u5b66", "spname": "\u8d22\u52a1\u7ba1\u7406", "average": 534, "max": 537, "min": 532}, {"schoolName": "\u6c5f\u82cf\u5927\u5b66", "spname": "\u4f1a\u8ba1\u5b66", "average": 554, "max": 554, "min": 554}, {"schoolName": "\u5c71\u4e1c\u5e08\u8303\u5927\u5b66", "spname": "\u4e2d\u56fd\u8bed\u8a00\u6587\u5b66\u7c7b", "average": 557, "max": 559, "min": 554}, {"schoolName": "\u5b81\u590f\u5927\u5b66", "spname": "\u5b66\u524d\u6559\u80b2\uff08\u6559\u5e08\u6559\u80b2\uff09", "average": 528, "max": 548, "min": 509}, {"schoolName": "\u5b81\u590f\u5927\u5b66", "spname": "\u82f1\u8bed\uff08\u6559\u5e08\u6559\u80b2\uff09", "average": 528, "max": 548, "min": 509}, {"schoolName": "\u5b81\u590f\u5927\u5b66", "spname": "\u963f\u62c9\u4f2f\u8bed", "average": 529, "max": 549, "min": 509}, {"schoolName": "\u592a\u539f\u7406\u5de5\u5927\u5b66", "spname": "\u5e02\u573a\u8425\u9500", "average": 540, "max": 543, "min": 537}, {"schoolName": "\u592a\u539f\u7406\u5de5\u5927\u5b66", "spname": "\u82f1\u8bed", "average": 540, "max": 543, "min": 538}, {"schoolName": "\u592a\u539f\u7406\u5de5\u5927\u5b66", "spname": "\u82f1\u8bed\uff08\u82f1\u4fc4\u53cc\u8bed\u65b9\u5411\uff09", "average": 539, "max": 539, "min": 539}, {"schoolName": "\u592a\u539f\u7406\u5de5\u5927\u5b66", "spname": "\u601d\u60f3\u653f\u6cbb\u6559\u80b2", "average": 542, "max": 547, "min": 539}, {"schoolName": "\u592a\u539f\u7406\u5de5\u5927\u5b66", "spname": "\u6c49\u8bed\u56fd\u9645\u6559\u80b2", "average": 544, "max": 549, "min": 541}, {"schoolName": "\u592a\u539f\u7406\u5de5\u5927\u5b66", "spname": "\u6cd5\u5b66", "average": 546, "max": 547, "min": 544}, {"schoolName": "\u592a\u539f\u7406\u5de5\u5927\u5b66", "spname": "\u56fd\u9645\u7ecf\u6d4e\u4e0e\u8d38\u6613", "average": 546, "max": 547, "min": 546}, {"schoolName": "\u897f\u5b89\u5916\u56fd\u8bed\u5927\u5b66", "spname": "\u571f\u8033\u5176\u8bed", "average": 529, "max": 537, "min": 523}, {"schoolName": "\u6c5f\u82cf\u5927\u5b66", "spname": "\u91d1\u878d\u5b66", "average": 547, "max": 547, "min": 547}, {"schoolName": "\u957f\u6c5f\u5927\u5b66", "spname": "\u82f1\u8bed\uff08\u5e08\u8303\u7c7b\uff09", "average": 528, "max": 528, "min": 528}, {"schoolName": "\u5b81\u590f\u5927\u5b66", "spname": "\u6c49\u8bed\u8a00\u6587\u5b66\uff08\u6559\u5e08\u6559\u80b2\uff09", "average": 530, "max": 552, "min": 509}, {"schoolName": "\u5929\u6d25\u5e08\u8303\u5927\u5b66", "spname": "\u6c49\u8bed\u8a00\u6587\u5b66", "average": 529, "max": 532, "min": 526}, {"schoolName": "\u5929\u6d25\u5de5\u4e1a\u5927\u5b66", "spname": "\u5e7f\u544a\u5b66", "average": 532, "max": 534, "min": 531}, {"schoolName": "\u5927\u8fde\u5916\u56fd\u8bed\u5927\u5b66", "spname": "\u56fd\u9645\u4e8b\u52a1\u4e0e\u56fd\u9645\u5173\u7cfb", "average": 530, "max": 534, "min": 527}, {"schoolName": "\u5927\u8fde\u5916\u56fd\u8bed\u5927\u5b66", "spname": "\u82f1\u8bed", "average": 539, "max": 543, "min": 534}, {"schoolName": "\u5927\u8fde\u5916\u56fd\u8bed\u5927\u5b66", "spname": "\u65e5\u8bed", "average": 535, "max": 536, "min": 534}, {"schoolName": "\u5927\u8fde\u5916\u56fd\u8bed\u5927\u5b66", "spname": "\u6cd5\u8bed", "average": 544, "max": 549, "min": 538}, {"schoolName": "\u56db\u5ddd\u5e08\u8303\u5927\u5b66", "spname": "\u601d\u60f3\u653f\u6cbb\u6559\u80b2", "average": 528, "max": 530, "min": 526}, {"schoolName": "\u56db\u5ddd\u5e08\u8303\u5927\u5b66", "spname": "\u82f1\u8bed", "average": 530, "max": 531, "min": 529}, {"schoolName": "\u56db\u5ddd\u5e08\u8303\u5927\u5b66", "spname": "\u6c49\u8bed\u8a00\u6587\u5b66", "average": 535, "max": 537, "min": 533}, {"schoolName": "\u56db\u5ddd\u5e08\u8303\u5927\u5b66", "spname": "\u56fd\u9645\u7ecf\u6d4e\u4e0e\u8d38\u6613", "average": 533, "max": 533, "min": 533}, {"schoolName": "\u56db\u5ddd\u5e08\u8303\u5927\u5b66", "spname": "\u6559\u80b2\u5b66", "average": 555, "max": 555, "min": 555}, {"schoolName": "\u6e56\u5357\u79d1\u6280\u5927\u5b66", "spname": "\u601d\u60f3\u653f\u6cbb\u6559\u80b2", "average": 530, "max": 537, "min": 522}, {"schoolName": "\u56db\u5ddd\u5e08\u8303\u5927\u5b66", "spname": "\u5e7f\u64ad\u7535\u89c6\u5b66", "average": 534, "max": 541, "min": 526}, {"schoolName": "\u9ed1\u9f99\u6c5f\u5927\u5b66", "spname": "\u963f\u62c9\u4f2f\u8bed", "average": 529, "max": 529, "min": 529}, {"schoolName": "\u897f\u5317\u653f\u6cd5\u5927\u5b66", "spname": "\u6cd5\u5b66\uff08\u5211\u4e8b\u6cd5\uff09", "average": 534, "max": 570, "min": 523}, {"schoolName": "\u592a\u539f\u7406\u5de5\u5927\u5b66", "spname": "\u4f1a\u8ba1\u5b66", "average": 548, "max": 548, "min": 548}, {"schoolName": "\u897f\u5b89\u5916\u56fd\u8bed\u5927\u5b66", "spname": "\u91d1\u878d\u5b66", "average": 536, "max": 556, "min": 524}, {"schoolName": "\u897f\u5317\u653f\u6cd5\u5927\u5b66", "spname": "\u6cd5\u5b66\uff08\u53cd\u6050\u6016\u4e3b\u4e49\uff09", "average": 531, "max": 555, "min": 521}, {"schoolName": "\u6b66\u6c49\u79d1\u6280\u5927\u5b66", "spname": "\u4f1a\u8ba1\u5b66", "average": 545, "max": 545, "min": 544}, {"schoolName": "\u6e58\u6f6d\u5927\u5b66", "spname": "\u7ffb\u8bd1", "average": 548, "max": 554, "min": 543}, {"schoolName": "\u5927\u8fde\u5916\u56fd\u8bed\u5927\u5b66", "spname": "\u5fb7\u8bed", "average": 537, "max": 538, "min": 536}, {"schoolName": "\u6d77\u5357\u5927\u5b66", "spname": "\u516c\u5171\u7ba1\u7406\u7c7b", "average": 546, "max": 549, "min": 545}, {"schoolName": "\u897f\u5317\u653f\u6cd5\u5927\u5b66", "spname": "\u7535\u5b50\u5546\u52a1\u53ca\u6cd5\u5f8b", "average": 531, "max": 546, "min": 526}, {"schoolName": "\u897f\u5317\u653f\u6cd5\u5927\u5b66", "spname": "\u793e\u4f1a\u5b66", "average": 536, "max": 536, "min": 522}, {"schoolName": "\u897f\u5b89\u6587\u7406\u5b66\u9662", "spname": "\u5b66\u524d\u6559\u80b2", "average": 528, "max": 563, "min": 514}, {"schoolName": "\u897f\u5b89\u5916\u56fd\u8bed\u5927\u5b66", "spname": "\u963f\u62c9\u4f2f\u8bed", "average": 532, "max": 543, "min": 525}, {"schoolName": "\u6e58\u6f6d\u5927\u5b66", "spname": "\u7ecf\u6d4e\u5b66", "average": 545, "max": 549, "min": 543}, {"schoolName": "\u897f\u5317\u653f\u6cd5\u5927\u5b66", "spname": "\u516c\u5171\u4e8b\u4e1a\u7ba1\u7406", "average": 528, "max": 540, "min": 521}, {"schoolName": "\u5357\u4eac\u90ae\u7535\u5927\u5b66", "spname": "\u82f1\u8bed\uff08\u53ea\u62db\u82f1\u8bed\u8003\u751f\uff09", "average": 544, "max": 550, "min": 540}, {"schoolName": "\u5357\u4eac\u90ae\u7535\u5927\u5b66", "spname": "\u793e\u4f1a\u5de5\u4f5c", "average": 540, "max": 540, "min": 540}, {"schoolName": "\u5357\u4eac\u90ae\u7535\u5927\u5b66", "spname": "\u56fd\u9645\u7ecf\u6d4e\u4e0e\u8d38\u6613", "average": 544, "max": 544, "min": 543}, {"schoolName": "\u5357\u4eac\u90ae\u7535\u5927\u5b66", "spname": "\u5de5\u5546\u7ba1\u7406", "average": 551, "max": 552, "min": 550}, {"schoolName": "\u6d77\u5357\u5927\u5b66", "spname": "\u4e2d\u56fd\u8bed\u8a00\u6587\u5b66\u7c7b", "average": 546, "max": 553, "min": 541}, {"schoolName": "\u5357\u4eac\u4fe1\u606f\u5de5\u7a0b\u5927\u5b66", "spname": "\u5e02\u573a\u8425\u9500", "average": 533, "max": 534, "min": 533}, {"schoolName": "\u5357\u4eac\u4fe1\u606f\u5de5\u7a0b\u5927\u5b66", "spname": "\u4eba\u529b\u8d44\u6e90\u7ba1\u7406", "average": 544, "max": 555, "min": 536}, {"schoolName": "\u534e\u4fa8\u5927\u5b66", "spname": "\u5e94\u7528\u8bed\u8a00\u5b66", "average": 543, "max": 545, "min": 542}, {"schoolName": "\u534e\u4fa8\u5927\u5b66", "spname": "\u82f1\u8bed", "average": 545, "max": 549, "min": 542}, {"schoolName": "\u534e\u4fa8\u5927\u5b66", "spname": "\u6cd5\u5b66", "average": 549, "max": 556, "min": 543}, {"schoolName": "\u534e\u4fa8\u5927\u5b66", "spname": "\u56fd\u9645\u7ecf\u6d4e\u4e0e\u8d38\u6613", "average": 546, "max": 547, "min": 545}, {"schoolName": "\u534e\u4fa8\u5927\u5b66", "spname": "\u7ecf\u6d4e\u5b66\u7c7b\uff08\u4e2d\u7f8e\u8054\u5408\u57f9\u517b121\u56fd\u9645\u73ed,\u5168\u82f1\u6587\u6559\u5b66\uff09", "average": 554, "max": 563, "min": 546}, {"schoolName": "\u534e\u4fa8\u5927\u5b66", "spname": "\u6c49\u8bed\u56fd\u9645\u6559\u80b2", "average": 549, "max": 551, "min": 547}, {"schoolName": "\u534e\u4fa8\u5927\u5b66", "spname": "\u8d22\u52a1\u7ba1\u7406", "average": 551, "max": 553, "min": 549}, {"schoolName": "\u54c8\u5c14\u6ee8\u5546\u4e1a\u5927\u5b66", "spname": "\u4f1a\u8ba1\u5b66", "average": 545, "max": 552, "min": 537}, {"schoolName": "\u6e58\u6f6d\u5927\u5b66", "spname": "\u6cd5\u5b66\uff08\u5353\u8d8a\u73ed\uff09", "average": 558, "max": 560, "min": 555}, {"schoolName": "\u6e58\u6f6d\u5927\u5b66", "spname": "\u4f1a\u8ba1\u5b66", "average": 552, "max": 552, "min": 551}, {"schoolName": "\u957f\u5b89\u5927\u5b66", "spname": "\u5efa\u7b51\u7c7b\uff08\u5206\u6d41\u4e13\u4e1a\uff1a\u5efa\u7b51\u5b66\u3001\u57ce\u4e61\u89c4\u5212\uff09", "average": 558, "max": 562, "min": 554}, {"schoolName": "\u897f\u5317\u653f\u6cd5\u5927\u5b66", "spname": "\u5e02\u573a\u8425\u9500", "average": 528, "max": 536, "min": 521}, {"schoolName": "\u592a\u539f\u7406\u5de5\u5927\u5b66", "spname": "\u82f1\u8bed\uff08\u82f1\u65e5\u53cc\u8bed\u65b9\u5411\uff09", "average": 540, "max": 540, "min": 539}, {"schoolName": "\u6e58\u6f6d\u5927\u5b66", "spname": "\u91d1\u878d\u5b66", "average": 554, "max": 556, "min": 551}, {"schoolName": "\u5317\u4eac\u5370\u5237\u5b66\u9662", "spname": "\u7f16\u8f91\u51fa\u7248\u5b66", "average": 534, "max": 534, "min": 534}, {"schoolName": "\u5317\u4eac\u5316\u5de5\u5927\u5b66", "spname": "\u7269\u6d41\u7ba1\u7406", "average": 556, "max": 558, "min": 554}, {"schoolName": "\u897f\u5b89\u5916\u56fd\u8bed\u5927\u5b66", "spname": "\u6c49\u8bed\u8a00\u6587\u5b66", "average": 534, "max": 561, "min": 525}, {"schoolName": "\u5317\u4eac\u5370\u5237\u5b66\u9662", "spname": "\u6570\u5b57\u51fa\u7248", "average": 544, "max": 544, "min": 544}, {"schoolName": "\u897f\u5357\u77f3\u6cb9\u5927\u5b66", "spname": "\u7535\u5b50\u5546\u52a1", "average": 534, "max": 535, "min": 533}, {"schoolName": "\u5317\u4eac\u4fe1\u606f\u79d1\u6280\u5927\u5b66", "spname": "\u5e02\u573a\u8425\u9500\uff08\u54c1\u724c\u7ba1\u7406\uff09", "average": 546, "max": 547, "min": 545}, {"schoolName": "\u6d77\u5357\u5927\u5b66", "spname": "\u65c5\u6e38\u7ba1\u7406\u7c7b", "average": 549, "max": 554, "min": 546}, {"schoolName": "\u5185\u8499\u53e4\u5927\u5b66", "spname": "\u793e\u4f1a\u5de5\u4f5c", "average": 540, "max": 540, "min": 540}, {"schoolName": "\u5185\u8499\u53e4\u5927\u5b66", "spname": "\u793e\u4f1a\u5b66", "average": 540, "max": 540, "min": 540}, {"schoolName": "\u5185\u8499\u53e4\u5927\u5b66", "spname": "\u54f2\u5b66\uff08\u6587\u53f2\u54f2\u57fa\u5730\uff09", "average": 542, "max": 542, "min": 542}, {"schoolName": "\u5185\u8499\u53e4\u5927\u5b66", "spname": "\u6cd5\u5b66", "average": 545, "max": 547, "min": 543}, {"schoolName": "\u5185\u8499\u53e4\u5927\u5b66", "spname": "\u884c\u653f\u7ba1\u7406", "average": 545, "max": 545, "min": 545}, {"schoolName": "\u5929\u6d25\u5de5\u4e1a\u5927\u5b66", "spname": "\u4f1a\u8ba1\u5b66", "average": 535, "max": 535, "min": 535}, {"schoolName": "\u5317\u4eac\u5316\u5de5\u5927\u5b66", "spname": "\u5de5\u5546\u7ba1\u7406", "average": 557, "max": 557, "min": 557}, {"schoolName": "\u6cb3\u5317\u5de5\u4e1a\u5927\u5b66", "spname": "\u52b3\u52a8\u4e0e\u793e\u4f1a\u4fdd\u969c", "average": 551, "max": 554, "min": 548}, {"schoolName": "\u5185\u8499\u53e4\u5927\u5b66", "spname": "\u65b0\u95fb\u5b66", "average": 541, "max": 541, "min": 541}, {"schoolName": "\u534e\u4fa8\u5927\u5b66", "spname": "\u65b0\u95fb\u5b66", "average": 549, "max": 553, "min": 544}, {"schoolName": "\u5c71\u4e1c\u8d22\u7ecf\u5927\u5b66", "spname": "\u4f1a\u8ba1\u5b66", "average": 540, "max": 540, "min": 540}, {"schoolName": "\u9ed1\u9f99\u6c5f\u5927\u5b66", "spname": "\u6cd5\u8bed", "average": 528, "max": 528, "min": 528}, {"schoolName": "\u5357\u4eac\u4fe1\u606f\u5de5\u7a0b\u5927\u5b66", "spname": "\u6c49\u8bed\u8a00\u6587\u5b66", "average": 547, "max": 557, "min": 542}, {"schoolName": "\u4e91\u5357\u5927\u5b66", "spname": "\u7f05\u7538\u8bed", "average": 556, "max": 557, "min": 554}, {"schoolName": "\u4e91\u5357\u5927\u5b66", "spname": "\u8d8a\u5357\u8bed", "average": 558, "max": 563, "min": 554}, {"schoolName": "\u4e91\u5357\u5927\u5b66", "spname": "\u5e7f\u64ad\u7535\u89c6\u5b66", "average": 555, "max": 556, "min": 555}, {"schoolName": "\u4e91\u5357\u5927\u5b66", "spname": "\u4fe1\u606f\u7ba1\u7406\u4e0e\u4fe1\u606f\u7cfb\u7edf", "average": 555, "max": 555, "min": 555}, {"schoolName": "\u4e91\u5357\u5927\u5b66", "spname": "\u516c\u5171\u4e8b\u4e1a\u7ba1\u7406", "average": 556, "max": 556, "min": 555}, {"schoolName": "\u4e91\u5357\u5927\u5b66", "spname": "\u82f1\u8bed", "average": 557, "max": 558, "min": 556}, {"schoolName": "\u4e91\u5357\u5927\u5b66", "spname": "\u793e\u4f1a\u5de5\u4f5c", "average": 556, "max": 556, "min": 556}, {"schoolName": "\u4e91\u5357\u5927\u5b66", "spname": "\u7981\u6bd2\u5b66", "average": 557, "max": 557, "min": 557}, {"schoolName": "\u5185\u8499\u53e4\u5927\u5b66", "spname": "\u6c49\u8bed\u8a00\u6587\u5b66\uff08\u6587\u53f2\u54f2\u57fa\u5730\uff09", "average": 557, "max": 557, "min": 557}, {"schoolName": "\u54c8\u5c14\u6ee8\u5546\u4e1a\u5927\u5b66", "spname": "\u8d22\u52a1\u7ba1\u7406", "average": 528, "max": 531, "min": 524}, {"schoolName": "\u5317\u4eac\u5316\u5de5\u5927\u5b66", "spname": "\u516c\u5171\u7ba1\u7406\u7c7b", "average": 556, "max": 557, "min": 555}, {"schoolName": "\u6d77\u5357\u5927\u5b66", "spname": "\u65b0\u95fb\u4f20\u64ad\u5b66\u7c7b", "average": 547, "max": 548, "min": 546}, {"schoolName": "\u8fbd\u5b81\u5927\u5b66", "spname": "\u7ecf\u6d4e\u5b66\u7c7b\uff08\u7ecf\u6d4e\u5b66\u3001\u7ecf\u6d4e\u7edf\u8ba1\u5b66\u3001\u56fd\u6c11\u7ecf\u6d4e\u7ba1\u7406\uff09", "average": 558, "max": 558, "min": 557}, {"schoolName": "\u897f\u5317\u653f\u6cd5\u5927\u5b66", "spname": "\u653f\u6cbb\u5b66\u4e0e\u884c\u653f\u5b66", "average": 531, "max": 539, "min": 521}, {"schoolName": "\u5357\u4eac\u90ae\u7535\u5927\u5b66", "spname": "\u516c\u5171\u4e8b\u4e1a\u7ba1\u7406", "average": 542, "max": 544, "min": 540}, {"schoolName": "\u5c71\u4e1c\u5e08\u8303\u5927\u5b66", "spname": "\u5730\u7406\u79d1\u5b66\u7c7b", "average": 549, "max": 551, "min": 546}, {"schoolName": "\u6e58\u6f6d\u5927\u5b66", "spname": "\u793e\u4f1a\u5b66", "average": 546, "max": 552, "min": 542}, {"schoolName": "\u5185\u8499\u53e4\u5927\u5b66", "spname": "\u82f1\u8bed", "average": 547, "max": 548, "min": 546}, {"schoolName": "\u4e2d\u56fd\u77ff\u4e1a\u5927\u5b66", "spname": "\u516c\u5171\u7ba1\u7406\u7c7b", "average": 548, "max": 554, "min": 544}, {"schoolName": "\u4e2d\u56fd\u77f3\u6cb9\u5927\u5b66\uff08\u534e\u4e1c\uff09", "spname": "\u82f1\u8bed\uff08\u6587\uff09", "average": 554, "max": 554, "min": 553}, {"schoolName": "\u5357\u4eac\u90ae\u7535\u5927\u5b66", "spname": "\u5e02\u573a\u8425\u9500", "average": 542, "max": 544, "min": 540}, {"schoolName": "\u5927\u8fde\u4ea4\u901a\u5927\u5b66", "spname": "\u5de5\u5546\u7ba1\u7406\u7c7b", "average": 554, "max": 554, "min": 553}, {"schoolName": "\u4e2d\u56fd\u77f3\u6cb9\u5927\u5b66\uff08\u534e\u4e1c\uff09", "spname": "\u82f1\u8bed", "average": 554, "max": 554, "min": 553}, {"schoolName": "\u54c8\u5c14\u6ee8\u5546\u4e1a\u5927\u5b66", "spname": "\u6cd5\u5b66", "average": 534, "max": 552, "min": 516}, {"schoolName": "\u4e2d\u56fd\u77f3\u6cb9\u5927\u5b66\uff08\u534e\u4e1c\uff09", "spname": "\u6cd5\u5b66\uff08\u6587\uff09", "average": 558, "max": 559, "min": 556}, {"schoolName": "\u5185\u8499\u53e4\u5927\u5b66", "spname": "\u653f\u6cbb\u5b66\u4e0e\u884c\u653f\u5b66", "average": 542, "max": 542, "min": 542}, {"schoolName": "\u8d35\u5dde\u5927\u5b66", "spname": "\u5916\u56fd\u8bed\u8a00\u6587\u5b66\u7c7b", "average": 539, "max": 540, "min": 538}, {"schoolName": "\u4e2d\u56fd\u6c11\u822a\u5927\u5b66", "spname": "\u4f1a\u8ba1\u5b66", "average": 557, "max": 562, "min": 551}, {"schoolName": "\u5185\u8499\u53e4\u5927\u5b66", "spname": "\u4fc4\u8bed", "average": 539, "max": 539, "min": 539}, {"schoolName": "\u5317\u4eac\u4fe1\u606f\u79d1\u6280\u5927\u5b66", "spname": "\u56fd\u9645\u7ecf\u6d4e\u4e0e\u8d38\u6613", "average": 550, "max": 553, "min": 547}, {"schoolName": "\u5185\u8499\u53e4\u5927\u5b66", "spname": "\u54f2\u5b66", "average": 540, "max": 540, "min": 540}, {"schoolName": "\u5927\u8fde\u6d77\u4e8b\u5927\u5b66", "spname": "\u793e\u4f1a\u5de5\u4f5c", "average": 551, "max": 555, "min": 549}, {"schoolName": "\u5ef6\u8fb9\u5927\u5b66", "spname": "\u6c49\u8bed\u8a00\u6587\u5b66", "average": 537, "max": 538, "min": 536}, {"schoolName": "\u897f\u5317\u653f\u6cd5\u5927\u5b66", "spname": "\u54f2\u5b66", "average": 534, "max": 552, "min": 522}, {"schoolName": "\u6e58\u6f6d\u5927\u5b66", "spname": "\u897f\u73ed\u7259\u8bed", "average": 549, "max": 555, "min": 543}, {"schoolName": "\u91cd\u5e86\u5de5\u5546\u5927\u5b66", "spname": "\u7269\u6d41\u7ba1\u7406", "average": 554, "max": 554, "min": 554}, {"schoolName": "\u897f\u5b89\u5916\u56fd\u8bed\u5927\u5b66", "spname": "\u6ce2\u5170\u8bed", "average": 548, "max": 588, "min": 537}, {"schoolName": "\u5ef6\u8fb9\u5927\u5b66", "spname": "\u5386\u53f2\u5b66", "average": 537, "max": 538, "min": 536}, {"schoolName": "\u5185\u8499\u53e4\u5927\u5b66", "spname": "\u52b3\u52a8\u4e0e\u793e\u4f1a\u4fdd\u969c", "average": 538, "max": 538, "min": 537}, {"schoolName": "\u4e2d\u56fd\u77ff\u4e1a\u5927\u5b66", "spname": "\u5916\u56fd\u8bed\u8a00\u6587\u5b66\u7c7b", "average": 547, "max": 548, "min": 546}, {"schoolName": "\u4e91\u5357\u5927\u5b66", "spname": "\u6c11\u65cf\u5b66", "average": 555, "max": 558, "min": 554}, {"schoolName": "\u6e58\u6f6d\u5927\u5b66", "spname": "\u5fb7\u8bed", "average": 552, "max": 553, "min": 550}, {"schoolName": "\u5c71\u4e1c\u5e08\u8303\u5927\u5b66", "spname": "\u5386\u53f2\u5b66\u7c7b", "average": 557, "max": 563, "min": 553}, {"schoolName": "\u5929\u6d25\u5de5\u4e1a\u5927\u5b66", "spname": "\u82f1\u8bed", "average": 528, "max": 532, "min": 523}, {"schoolName": "\u534e\u4fa8\u5927\u5b66", "spname": "\u7ecf\u6d4e\u5b66\u7c7b\uff08\u56fd\u9645\u7ecf\u6d4e\u4e0e\u8d38\u6613\u5168\u82f1\u6587\u6559\u5b66,\u4e2d\u7f8e\u8054\u5408\u57f9\u517b121\u56fd\u9645\u73ed\uff09", "average": 550, "max": 553, "min": 547}, {"schoolName": "\u5357\u4eac\u4fe1\u606f\u5de5\u7a0b\u5927\u5b66", "spname": "\u6c49\u8bed\u56fd\u9645\u6559\u80b2", "average": 547, "max": 547, "min": 547}, {"schoolName": "\u6d77\u5357\u5927\u5b66", "spname": "\u5de5\u5546\u7ba1\u7406\u7c7b", "average": 555, "max": 561, "min": 552}, {"schoolName": "\u5185\u8499\u53e4\u5927\u5b66", "spname": "\u516c\u5171\u4e8b\u4e1a\u7ba1\u7406", "average": 539, "max": 539, "min": 539}, {"schoolName": "\u534e\u4fa8\u5927\u5b66", "spname": "\u5de5\u5546\u7ba1\u7406\u7c7b\uff08\u65c5\u6e38\u7ba1\u7406\u5168\u82f1\u6587\u6559\u5b66,\u4e2d\u7f8e\u8054\u5408\u57f9\u517b121\u56fd\u9645\u73ed\uff09", "average": 544, "max": 545, "min": 542}, {"schoolName": "\u4e1c\u5317\u6797\u4e1a\u5927\u5b66", "spname": "\u793e\u4f1a\u5de5\u4f5c", "average": 534, "max": 534, "min": 534}, {"schoolName": "\u4e1c\u5317\u6797\u4e1a\u5927\u5b66", "spname": "\u7ecf\u6d4e\u5b66\u7c7b", "average": 551, "max": 551, "min": 551}, {"schoolName": "\u4e1c\u5317\u519c\u4e1a\u5927\u5b66", "spname": "\u519c\u6797\u7ecf\u6d4e\u7ba1\u7406", "average": 539, "max": 541, "min": 537}, {"schoolName": "\u77f3\u6cb3\u5b50\u5927\u5b66", "spname": "\u6c49\u8bed\u8a00\u6587\u5b66", "average": 528, "max": 536, "min": 520}, {"schoolName": "\u5317\u4eac\u4fe1\u606f\u79d1\u6280\u5927\u5b66", "spname": "\u4f20\u64ad\u5b66", "average": 548, "max": 552, "min": 543}, {"schoolName": "\u4e1c\u5317\u6797\u4e1a\u5927\u5b66", "spname": "\u5de5\u5546\u7ba1\u7406\u7c7b", "average": 541, "max": 542, "min": 539}, {"schoolName": "\u5317\u4eac\u4fe1\u606f\u79d1\u6280\u5927\u5b66", "spname": "\u4eba\u529b\u8d44\u6e90\u7ba1\u7406", "average": 544, "max": 545, "min": 544}, {"schoolName": "\u5929\u6d25\u5de5\u4e1a\u5927\u5b66", "spname": "\u6cd5\u5b66", "average": 534, "max": 538, "min": 530}, {"schoolName": "\u4e0a\u6d77\u653f\u6cd5\u5b66\u9662", "spname": "\u77e5\u8bc6\u4ea7\u6743", "average": 550, "max": 555, "min": 549}, {"schoolName": "\u5185\u8499\u53e4\u5927\u5b66", "spname": "\u65c5\u6e38\u7ba1\u7406", "average": 537, "max": 537, "min": 537}, {"schoolName": "\u5357\u4eac\u90ae\u7535\u5927\u5b66", "spname": "\u884c\u653f\u7ba1\u7406", "average": 545, "max": 548, "min": 542}, {"schoolName": "\u9ed1\u9f99\u6c5f\u4e2d\u533b\u836f\u5927\u5b66", "spname": "\u4e2d\u533b\u5b66", "average": 548, "max": 553, "min": 542}, {"schoolName": "\u534e\u4fa8\u5927\u5b66", "spname": "\u6c49\u8bed\u8a00\u6587\u5b66", "average": 545, "max": 546, "min": 544}, {"schoolName": "\u9ed1\u9f99\u6c5f\u5927\u5b66", "spname": "\u5fb7\u8bed", "average": 528, "max": 532, "min": 524}, {"schoolName": "\u5185\u8499\u53e4\u5927\u5b66", "spname": "\u5386\u53f2\u5b66\uff08\u6587\u53f2\u54f2\u57fa\u5730\uff09", "average": 546, "max": 546, "min": 546}, {"schoolName": "\u6e58\u6f6d\u5927\u5b66", "spname": "\u7ecf\u6d4e\u5b66\uff08\u97f6\u5cf0\u73ed\uff09", "average": 558, "max": 560, "min": 557}, {"schoolName": "\u5317\u4eac\u5e08\u8303\u5927\u5b66-\u9999\u6e2f\u6d78\u4f1a\u5927\u5b66\u8054\u5408\u56fd\u9645\u5b66\u9662", "spname": "\u8d22\u52a1\u7ba1\u7406", "average": 556, "max": "--", "min": "--"}, {"schoolName": "\u4e1c\u5317\u6797\u4e1a\u5927\u5b66", "spname": "\u5e7f\u544a\u5b66", "average": 533, "max": 533, "min": 533}, {"schoolName": "\u897f\u5317\u653f\u6cd5\u5927\u5b66", "spname": "\u82f1\u8bed", "average": 528, "max": 561, "min": 520}, {"schoolName": "\u592a\u539f\u7406\u5de5\u5927\u5b66", "spname": "\u884c\u653f\u7ba1\u7406", "average": 542, "max": 543, "min": 541}, {"schoolName": "\u5185\u8499\u53e4\u5927\u5b66", "spname": "\u5386\u53f2\u5b66", "average": 545, "max": 545, "min": 545}, {"schoolName": "\u6e58\u6f6d\u5927\u5b66", "spname": "\u6c49\u8bed\u8a00\u6587\u5b66", "average": 550, "max": 563, "min": 544}, {"schoolName": "\u4e1c\u5317\u519c\u4e1a\u5927\u5b66", "spname": "\u5de5\u5546\u7ba1\u7406\u7c7b\uff08\u7ba1\u7406\u5b66\u2161\uff09", "average": 534, "max": 544, "min": 528}, {"schoolName": "\u6e58\u6f6d\u5927\u5b66", "spname": "\u884c\u653f\u7ba1\u7406", "average": 542, "max": 544, "min": 542}, {"schoolName": "\u4e1c\u5317\u6797\u4e1a\u5927\u5b66", "spname": "\u653f\u6cbb\u5b66\u4e0e\u884c\u653f\u5b66", "average": 531, "max": 531, "min": 531}, {"schoolName": "\u897f\u5357\u77f3\u6cb9\u5927\u5b66", "spname": "\u82f1\u8bed", "average": 532, "max": 534, "min": 530}, {"schoolName": "\u5185\u8499\u53e4\u5927\u5b66", "spname": "\u65e5\u8bed", "average": 537, "max": 537, "min": 537}, {"schoolName": "\u6d77\u5357\u5927\u5b66", "spname": "\u5730\u7406\u79d1\u5b66\u7c7b\uff08\u4e2d\u5916\u5408\u4f5c\u529e\u5b66\uff09\uff08\u4eba\u6587\u5730\u7406\u4e0e\u57ce\u4e61\u89c4\u5212\uff09", "average": 548, "max": 548, "min": 548}, {"schoolName": "\u5185\u8499\u53e4\u5927\u5b66", "spname": "\u6c49\u8bed\u56fd\u9645\u6559\u80b2", "average": 540, "max": 540, "min": 540}, {"schoolName": "\u6e56\u5357\u79d1\u6280\u5927\u5b66", "spname": "\u4f1a\u8ba1\u5b66", "average": 529, "max": 535, "min": 523}, {"schoolName": "\u5185\u8499\u53e4\u5927\u5b66", "spname": "\u6c49\u8bed\u8a00\u6587\u5b66", "average": 556, "max": 556, "min": 556}, {"schoolName": "\u897f\u5317\u519c\u6797\u79d1\u6280\u5927\u5b66", "spname": "\u7ecf\u6d4e\u5b66\u7c7b", "average": 543, "max": 575, "min": 536}, {"schoolName": "\u5185\u8499\u53e4\u5927\u5b66", "spname": "\u6587\u7269\u4e0e\u535a\u7269\u9986\u5b66", "average": 541, "max": 541, "min": 541}, {"schoolName": "\u897f\u5357\u77f3\u6cb9\u5927\u5b66", "spname": "\u793e\u4f1a\u5de5\u4f5c", "average": 534, "max": 536, "min": 531}, {"schoolName": "\u897f\u5b89\u90ae\u7535\u5927\u5b66", "spname": "\u56fd\u9645\u7ecf\u6d4e\u4e0e\u8d38\u6613", "average": 530, "max": 545, "min": 525}, {"schoolName": "\u4e1c\u5317\u6797\u4e1a\u5927\u5b66", "spname": "\u6cd5\u5b66", "average": 542, "max": 549, "min": 536}, {"schoolName": "\u5b81\u590f\u5927\u5b66", "spname": "\u5730\u7406\u79d1\u5b66\uff08\u6559\u5e08\u6559\u80b2\uff09", "average": 528, "max": 546, "min": 509}, {"schoolName": "\u4e2d\u56fd\u77f3\u6cb9\u5927\u5b66\uff08\u534e\u4e1c\uff09", "spname": "\u6cd5\u5b66", "average": 558, "max": 559, "min": 556}]